palmers_agents_general/__init__.py
palmers_agents_general/async_base_mq_worker.py
palmers_agents_general/base_mq_worker.py
palmers_agents_general/blobs_handler.py
palmers_agents_general/db_handler.py
palmers_agents_general/models_handler.py
palmers_agents_general/utils.py
palmers_agents_general-0.0.40.dist-info/METADATA
palmers_agents_general-0.0.40.dist-info/WHEEL
palmers_agents_general-0.0.40.dist-info/licenses/LICENSE
palmers_agents_general-0.0.40.dist-info/RECORD
