Metadata-Version: 2.1
Name: palmers_agents_general
Version: 0.0.40
Summary: A package to preprocess data for Palmer's project
Project-URL: Homepage, https://github.com/pypa/sampleproject
Project-URL: Bug Tracker, https://github.com/pypa/sampleproject/issues
Author-email: Assaf <assafm@sdatta.ai>, Roy  <roy@sdatta.ai>, Guy <assafm@sdatta.ai>, Oran <assafm@sdatta.ai>, Yotam <assafm@sdatta.ai>
License-File: LICENSE
Classifier: License :: OSI Approved :: MIT License
Classifier: Operating System :: OS Independent
Classifier: Programming Language :: Python :: 3
Requires-Python: >=3.7
